{"meta":{"match_id":"650c6db6-683d-4523-aa64-d47345e228a3.nakama-0","match_key":"650c6db6-683d-4523-aa64-d47345e228a3","map_id":"AmbroseValley","date":"2026-02-11","duration_ms":268000,"humans":1,"bots":0,"rows":51,"event_counts":{"BotKill":1,"BotKilled":1,"Loot":15,"Position":34}},"players":[{"user_id":"92aa669f-1e40-43df-adbf-29462decf2d8","is_bot":false,"is_human":true,"path":[[55.81,488.52,0],[64.27,485.97,40000],[86.67,458.51,45000],[96.24,426.78,50000],[101.07,418.35,55000],[99.75,416.11,65000],[94.92,416.42,70000],[99.27,407.65,75000],[104.43,409.16,80000],[90.23,408.4,90000],[92.19,416.4,95000],[87.8,415.09,100000],[86.33,395.9,110000],[109.94,382.05,115000],[139.62,374.19,120000],[173.03,377.23,125000],[199.93,388.11,130000],[223.1,409.62,135000],[247.31,418.06,140000],[279.3,424.16,146000],[285.82,414.63,156000],[287.55,410.63,161000],[283.41,417.74,166000],[280.56,416.76,176000],[285.07,415.61,181000],[283.58,425.67,186000],[278.83,430.5,221000],[277.59,436.63,226000],[285.61,440.63,231000],[298.08,447.71,236000],[295.15,441.78,241000],[297.07,461.02,256000],[306.17,436.79,261000],[319.64,429.61,266000]],"events":[{"type":"Loot","px":101.55,"py":417.65,"t":59000,"x":-280.74,"z":59.93,"user_id":"92aa669f-1e40-43df-adbf-29462decf2d8","is_bot":false},{"type":"Loot","px":99.75,"py":416.11,"t":65000,"x":-282.33,"z":61.28,"user_id":"92aa669f-1e40-43df-adbf-29462decf2d8","is_bot":false},{"type":"Loot","px":94.92,"py":416.42,"t":71000,"x":-286.58,"z":61.0,"user_id":"92aa669f-1e40-43df-adbf-29462decf2d8","is_bot":false},{"type":"Loot","px":99.27,"py":407.65,"t":77000,"x":-282.76,"z":68.72,"user_id":"92aa669f-1e40-43df-adbf-29462decf2d8","is_bot":false},{"type":"Loot","px":104.43,"py":409.16,"t":82000,"x":-278.22,"z":67.39,"user_id":"92aa669f-1e40-43df-adbf-29462decf2d8","is_bot":false},{"type":"Loot","px":90.23,"py":408.4,"t":91000,"x":-290.7,"z":68.06,"user_id":"92aa669f-1e40-43df-adbf-29462decf2d8","is_bot":false},{"type":"Loot","px":90.23,"py":408.4,"t":91000,"x":-290.7,"z":68.06,"user_id":"92aa669f-1e40-43df-adbf-29462decf2d8","is_bot":false},{"type":"Loot","px":87.34,"py":417.78,"t":98000,"x":-293.24,"z":59.81,"user_id":"92aa669f-1e40-43df-adbf-29462decf2d8","is_bot":false},{"type":"Loot","px":87.8,"py":415.09,"t":101000,"x":-292.83,"z":62.18,"user_id":"92aa669f-1e40-43df-adbf-29462decf2d8","is_bot":false},{"type":"BotKill","px":280.99,"py":419.73,"t":172000,"x":-123.04,"z":58.1,"user_id":"92aa669f-1e40-43df-adbf-29462decf2d8","is_bot":false},{"type":"Loot","px":288.19,"py":415.15,"t":179000,"x":-116.71,"z":62.12,"user_id":"92aa669f-1e40-43df-adbf-29462decf2d8","is_bot":false},{"type":"Loot","px":288.19,"py":415.15,"t":179000,"x":-116.71,"z":62.12,"user_id":"92aa669f-1e40-43df-adbf-29462decf2d8","is_bot":false},{"type":"Loot","px":288.19,"py":415.15,"t":179000,"x":-116.71,"z":62.12,"user_id":"92aa669f-1e40-43df-adbf-29462decf2d8","is_bot":false},{"type":"Loot","px":283.58,"py":425.67,"t":212000,"x":-120.76,"z":52.87,"user_id":"92aa669f-1e40-43df-adbf-29462decf2d8","is_bot":false},{"type":"Loot","px":279.04,"py":429.6,"t":220000,"x":-124.75,"z":49.42,"user_id":"92aa669f-1e40-43df-adbf-29462decf2d8","is_bot":false},{"type":"Loot","px":277.59,"py":436.63,"t":225000,"x":-126.03,"z":43.24,"user_id":"92aa669f-1e40-43df-adbf-29462decf2d8","is_bot":false},{"type":"BotKilled","px":321.68,"py":433.45,"t":268000,"x":-87.27,"z":46.04,"user_id":"92aa669f-1e40-43df-adbf-29462decf2d8","is_bot":false}],"event_counts":{"BotKill":1,"BotKilled":1,"Loot":15,"Position":34}}],"timeline":[{"type":"Loot","px":101.55,"py":417.65,"t":59000,"x":-280.74,"z":59.93,"user_id":"92aa669f-1e40-43df-adbf-29462decf2d8","is_bot":false},{"type":"Loot","px":99.75,"py":416.11,"t":65000,"x":-282.33,"z":61.28,"user_id":"92aa669f-1e40-43df-adbf-29462decf2d8","is_bot":false},{"type":"Loot","px":94.92,"py":416.42,"t":71000,"x":-286.58,"z":61.0,"user_id":"92aa669f-1e40-43df-adbf-29462decf2d8","is_bot":false},{"type":"Loot","px":99.27,"py":407.65,"t":77000,"x":-282.76,"z":68.72,"user_id":"92aa669f-1e40-43df-adbf-29462decf2d8","is_bot":false},{"type":"Loot","px":104.43,"py":409.16,"t":82000,"x":-278.22,"z":67.39,"user_id":"92aa669f-1e40-43df-adbf-29462decf2d8","is_bot":false},{"type":"Loot","px":90.23,"py":408.4,"t":91000,"x":-290.7,"z":68.06,"user_id":"92aa669f-1e40-43df-adbf-29462decf2d8","is_bot":false},{"type":"Loot","px":90.23,"py":408.4,"t":91000,"x":-290.7,"z":68.06,"user_id":"92aa669f-1e40-43df-adbf-29462decf2d8","is_bot":false},{"type":"Loot","px":87.34,"py":417.78,"t":98000,"x":-293.24,"z":59.81,"user_id":"92aa669f-1e40-43df-adbf-29462decf2d8","is_bot":false},{"type":"Loot","px":87.8,"py":415.09,"t":101000,"x":-292.83,"z":62.18,"user_id":"92aa669f-1e40-43df-adbf-29462decf2d8","is_bot":false},{"type":"BotKill","px":280.99,"py":419.73,"t":172000,"x":-123.04,"z":58.1,"user_id":"92aa669f-1e40-43df-adbf-29462decf2d8","is_bot":false},{"type":"Loot","px":288.19,"py":415.15,"t":179000,"x":-116.71,"z":62.12,"user_id":"92aa669f-1e40-43df-adbf-29462decf2d8","is_bot":false},{"type":"Loot","px":288.19,"py":415.15,"t":179000,"x":-116.71,"z":62.12,"user_id":"92aa669f-1e40-43df-adbf-29462decf2d8","is_bot":false},{"type":"Loot","px":288.19,"py":415.15,"t":179000,"x":-116.71,"z":62.12,"user_id":"92aa669f-1e40-43df-adbf-29462decf2d8","is_bot":false},{"type":"Loot","px":283.58,"py":425.67,"t":212000,"x":-120.76,"z":52.87,"user_id":"92aa669f-1e40-43df-adbf-29462decf2d8","is_bot":false},{"type":"Loot","px":279.04,"py":429.6,"t":220000,"x":-124.75,"z":49.42,"user_id":"92aa669f-1e40-43df-adbf-29462decf2d8","is_bot":false},{"type":"Loot","px":277.59,"py":436.63,"t":225000,"x":-126.03,"z":43.24,"user_id":"92aa669f-1e40-43df-adbf-29462decf2d8","is_bot":false},{"type":"BotKilled","px":321.68,"py":433.45,"t":268000,"x":-87.27,"z":46.04,"user_id":"92aa669f-1e40-43df-adbf-29462decf2d8","is_bot":false}]}